zensols/deeplearn/resources/batch.conf
zensols/deeplearn/resources/cli-crossval.conf
zensols/deeplearn/resources/cli-pack.conf
zensols/deeplearn/resources/cli.conf
zensols/deeplearn/resources/default.conf
zensols/deeplearn/resources/model.conf
zensols/deeplearn/resources/obj.conf
zensols/deeplearn/resources/observer.conf
zensols/deeplearn/resources/torch.conf
zensols/dataframe/__init__.py
zensols/dataframe/config.py
zensols/dataframe/stash.py
zensols/dataset/__init__.py
zensols/dataset/dimreduce.py
zensols/dataset/interface.py
zensols/dataset/leaveout.py
zensols/dataset/multilabel.py
zensols/dataset/outlier.py
zensols/dataset/split.py
zensols/dataset/stash.py
zensols/deeplearn/__init__.py
zensols/deeplearn/cli.py
zensols/deeplearn/clicv.py
zensols/deeplearn/domain.py
zensols/deeplearn/multi.py
zensols/deeplearn/observer.py
zensols/deeplearn/torchconfig.py
zensols/deeplearn/torchtype.py
zensols/deeplearn/batch/__init__.py
zensols/deeplearn/batch/domain.py
zensols/deeplearn/batch/interface.py
zensols/deeplearn/batch/mapping.py
zensols/deeplearn/batch/meta.py
zensols/deeplearn/batch/stash.py
zensols/deeplearn/dataframe/__init__.py
zensols/deeplearn/dataframe/batch.py
zensols/deeplearn/dataframe/util.py
zensols/deeplearn/dataframe/vectorize.py
zensols/deeplearn/layer/__init__.py
zensols/deeplearn/layer/conv.py
zensols/deeplearn/layer/crf.py
zensols/deeplearn/layer/linear.py
zensols/deeplearn/layer/recur.py
zensols/deeplearn/layer/recurcrf.py
zensols/deeplearn/model/__init__.py
zensols/deeplearn/model/analyze.py
zensols/deeplearn/model/batchiter.py
zensols/deeplearn/model/executor.py
zensols/deeplearn/model/facade.py
zensols/deeplearn/model/format.py
zensols/deeplearn/model/manager.py
zensols/deeplearn/model/meta.py
zensols/deeplearn/model/module.py
zensols/deeplearn/model/multilabel.py
zensols/deeplearn/model/optimizer.py
zensols/deeplearn/model/pack.py
zensols/deeplearn/model/pred.py
zensols/deeplearn/model/sequence.py
zensols/deeplearn/model/trainmng.py
zensols_deeplearn-1.15.0.dist-info/METADATA
zensols_deeplearn-1.15.0.dist-info/WHEEL
zensols_deeplearn-1.15.0.dist-info/licenses/LICENSE.md
zensols_deeplearn-1.15.0.dist-info/RECORD
