Metadata-Version: 2.3
Name: zensols_deeplearn
Version: 1.15.0
Summary: This deep learning library was designed to provide consistent and reproducible results.
Project-URL: Homepage, https://github.com/plandes/deeplearn
Project-URL: Documentation, https://plandes.github.io/deeplearn
Project-URL: Repository, https://github.com/plandes/deeplearn.git
Project-URL: Issues, https://github.com/plandes/deeplearn/issues
Project-URL: Changelog, https://github.com/plandes/deeplearn/blob/master/CHANGELOG.md
Author-email: Paul Landes <landes@mailc.net>
License: MIT
Keywords: deep learning,pytorch
Requires-Python: <3.15,>=3.11
Requires-Dist: iterative-stratification~=0.1.9
Requires-Dist: scikit-learn~=1.8.0
Requires-Dist: scipy~=1.16.3
Requires-Dist: torchvision
Requires-Dist: torch~=2.7.1
Requires-Dist: tqdm
Requires-Dist: zensols-datdesc~=1.4.2
Requires-Dist: zensols-install~=1.4.0
